[
  {
    "axis": "foundry",
    "company": "globalfoundries",
    "category": "news",
    "headline": "8-K  - Current report",
    "url": "https://www.sec.gov/Archives/edgar/data/1826397/000149315226027977/0001493152-26-027977-index.htm",
    "published_date": "2026-06-09",
    "source": "GlobalFoundries",
    "tags": null,
    "summary": null
  },
  {
    "axis": "foundry",
    "company": "globalfoundries",
    "category": "news",
    "headline": "8-K  - Current report",
    "url": "https://www.sec.gov/Archives/edgar/data/1826397/000149315226026380/0001493152-26-026380-index.htm",
    "published_date": "2026-05-29",
    "source": "GlobalFoundries",
    "tags": null,
    "summary": null
  },
  {
    "axis": "foundry",
    "company": "globalfoundries",
    "category": "news",
    "headline": "8-K  - Current report",
    "url": "https://www.sec.gov/Archives/edgar/data/1826397/000149315226023917/0001493152-26-023917-index.htm",
    "published_date": "2026-05-15",
    "source": "GlobalFoundries",
    "tags": null,
    "summary": null
  },
  {
    "axis": "foundry",
    "company": "globalfoundries",
    "category": "news",
    "headline": "8-K  - Current report",
    "url": "https://www.sec.gov/Archives/edgar/data/1826397/000149315226018940/0001493152-26-018940-index.htm",
    "published_date": "2026-04-24",
    "source": "GlobalFoundries",
    "tags": null,
    "summary": null
  },
  {
    "axis": "foundry",
    "company": "globalfoundries",
    "category": "news",
    "headline": "8-K  - Current report",
    "url": "https://www.sec.gov/Archives/edgar/data/1826397/000149315226011633/0001493152-26-011633-index.htm",
    "published_date": "2026-03-19",
    "source": "GlobalFoundries",
    "tags": null,
    "summary": null
  },
  {
    "axis": "foundry",
    "company": "globalfoundries",
    "category": "news",
    "headline": "8-K  - Current report",
    "url": "https://www.sec.gov/Archives/edgar/data/1826397/000149315226011248/0001493152-26-011248-index.htm",
    "published_date": "2026-03-18",
    "source": "GlobalFoundries",
    "tags": null,
    "summary": null
  },
  {
    "axis": "foundry",
    "company": "globalfoundries",
    "category": "news",
    "headline": "8-K  - Current report",
    "url": "https://www.sec.gov/Archives/edgar/data/1826397/000149315226004069/0001493152-26-004069-index.htm",
    "published_date": "2026-01-28",
    "source": "GlobalFoundries",
    "tags": null,
    "summary": null
  },
  {
    "axis": "foundry",
    "company": "globalfoundries",
    "category": "news",
    "headline": "8-K  - Current report",
    "url": "https://www.sec.gov/Archives/edgar/data/1826397/000149315226003716/0001493152-26-003716-index.htm",
    "published_date": "2026-01-27",
    "source": "GlobalFoundries",
    "tags": null,
    "summary": null
  },
  {
    "axis": "foundry",
    "company": "globalfoundries",
    "category": "news",
    "headline": "8-K  - Current report",
    "url": "https://www.sec.gov/Archives/edgar/data/1826397/000149315226003637/0001493152-26-003637-index.htm",
    "published_date": "2026-01-26",
    "source": "GlobalFoundries",
    "tags": null,
    "summary": null
  },
  {
    "axis": "foundry",
    "company": "globalfoundries",
    "category": "news",
    "headline": "8-K  - Current report",
    "url": "https://www.sec.gov/Archives/edgar/data/1826397/000149315225024469/0001493152-25-024469-index.htm",
    "published_date": "2025-11-20",
    "source": "GlobalFoundries",
    "tags": null,
    "summary": null
  },
  {
    "axis": "foundry",
    "company": "globalfoundries",
    "category": "news",
    "headline": "8-K  - Current report",
    "url": "https://www.sec.gov/Archives/edgar/data/1826397/000149315225022400/0001493152-25-022400-index.htm",
    "published_date": "2025-11-13",
    "source": "GlobalFoundries",
    "tags": null,
    "summary": null
  },
  {
    "axis": "foundry",
    "company": "globalfoundries",
    "category": "news",
    "headline": "8-K  - Current report",
    "url": "https://www.sec.gov/Archives/edgar/data/1826397/000149315225021948/0001493152-25-021948-index.htm",
    "published_date": "2025-11-12",
    "source": "GlobalFoundries",
    "tags": null,
    "summary": null
  },
  {
    "axis": "foundry",
    "company": "globalfoundries",
    "category": "news",
    "headline": "8-K  - Current report",
    "url": "https://www.sec.gov/Archives/edgar/data/1826397/000149315225021006/0001493152-25-021006-index.htm",
    "published_date": "2025-11-06",
    "source": "GlobalFoundries",
    "tags": null,
    "summary": null
  },
  {
    "axis": "foundry",
    "company": "globalfoundries",
    "category": "news",
    "headline": "8-K  - Current report",
    "url": "https://www.sec.gov/Archives/edgar/data/1826397/000149315225019747/0001493152-25-019747-index.htm",
    "published_date": "2025-10-27",
    "source": "GlobalFoundries",
    "tags": null,
    "summary": null
  },
  {
    "axis": "foundry",
    "company": "globalfoundries",
    "category": "news",
    "headline": "8-K  - Current report",
    "url": "https://www.sec.gov/Archives/edgar/data/1826397/000149315225019013/0001493152-25-019013-index.htm",
    "published_date": "2025-10-23",
    "source": "GlobalFoundries",
    "tags": null,
    "summary": null
  },
  {
    "axis": "foundry",
    "company": "globalfoundries",
    "category": "news",
    "headline": "8-K  - Current report",
    "url": "https://www.sec.gov/Archives/edgar/data/1826397/000149315225014385/0001493152-25-014385-index.htm",
    "published_date": "2025-09-22",
    "source": "GlobalFoundries",
    "tags": null,
    "summary": null
  },
  {
    "axis": "foundry",
    "company": "globalfoundries",
    "category": "news",
    "headline": "8-K  - Current report",
    "url": "https://www.sec.gov/Archives/edgar/data/1826397/000149315225013992/0001493152-25-013992-index.htm",
    "published_date": "2025-09-18",
    "source": "GlobalFoundries",
    "tags": null,
    "summary": null
  },
  {
    "axis": "foundry",
    "company": "globalfoundries",
    "category": "news",
    "headline": "8-K  - Current report",
    "url": "https://www.sec.gov/Archives/edgar/data/1826397/000164117225022238/0001641172-25-022238-index.htm",
    "published_date": "2025-08-05",
    "source": "GlobalFoundries",
    "tags": null,
    "summary": null
  },
  {
    "axis": "foundry",
    "company": "globalfoundries",
    "category": "news",
    "headline": "8-K  - Current report",
    "url": "https://www.sec.gov/Archives/edgar/data/1826397/000164117225014101/0001641172-25-014101-index.htm",
    "published_date": "2025-06-06",
    "source": "GlobalFoundries",
    "tags": null,
    "summary": null
  },
  {
    "axis": "foundry",
    "company": "globalfoundries",
    "category": "news",
    "headline": "8-K  - Current report",
    "url": "https://www.sec.gov/Archives/edgar/data/1826397/000164117225009082/0001641172-25-009082-index.htm",
    "published_date": "2025-05-07",
    "source": "GlobalFoundries",
    "tags": null,
    "summary": null
  },
  {
    "axis": "foundry",
    "company": "globalfoundries",
    "category": "news",
    "headline": "8-K  - Current report",
    "url": "https://www.sec.gov/Archives/edgar/data/1826397/000164117225008121/0001641172-25-008121-index.htm",
    "published_date": "2025-05-01",
    "source": "GlobalFoundries",
    "tags": null,
    "summary": null
  },
  {
    "axis": "foundry",
    "company": "globalfoundries",
    "category": "news",
    "headline": "8-K  - Current report",
    "url": "https://www.sec.gov/Archives/edgar/data/1826397/000164117225006275/0001641172-25-006275-index.htm",
    "published_date": "2025-04-25",
    "source": "GlobalFoundries",
    "tags": null,
    "summary": null
  },
  {
    "axis": "foundry",
    "company": "globalfoundries",
    "category": "news",
    "headline": "8-K/A [Amend]  - Current report",
    "url": "https://www.sec.gov/Archives/edgar/data/1826397/000164117225002981/0001641172-25-002981-index.htm",
    "published_date": "2025-04-07",
    "source": "GlobalFoundries",
    "tags": null,
    "summary": null
  },
  {
    "axis": "foundry",
    "company": "globalfoundries",
    "category": "news",
    "headline": "8-K  - Current report",
    "url": "https://www.sec.gov/Archives/edgar/data/1826397/000149315225009709/0001493152-25-009709-index.htm",
    "published_date": "2025-03-10",
    "source": "GlobalFoundries",
    "tags": null,
    "summary": null
  },
  {
    "axis": "foundry",
    "company": "globalfoundries",
    "category": "news",
    "headline": "8-K  - Current report",
    "url": "https://www.sec.gov/Archives/edgar/data/1826397/000149315225004221/0001493152-25-004221-index.htm",
    "published_date": "2025-01-30",
    "source": "GlobalFoundries",
    "tags": null,
    "summary": null
  },
  {
    "axis": "foundry",
    "company": "globalfoundries",
    "category": "news",
    "headline": "8-K  - Current report",
    "url": "https://www.sec.gov/Archives/edgar/data/1826397/000149315225003505/0001493152-25-003505-index.htm",
    "published_date": "2025-01-24",
    "source": "GlobalFoundries",
    "tags": null,
    "summary": null
  },
  {
    "axis": "foundry",
    "company": "globalfoundries",
    "category": "news",
    "headline": "8-K  - Current report",
    "url": "https://www.sec.gov/Archives/edgar/data/1826397/000149315225002585/0001493152-25-002585-index.htm",
    "published_date": "2025-01-16",
    "source": "GlobalFoundries",
    "tags": null,
    "summary": null
  },
  {
    "axis": "foundry",
    "company": "globalfoundries",
    "category": "news",
    "headline": "8-K  - Current report",
    "url": "https://www.sec.gov/Archives/edgar/data/1826397/000149315224048692/0001493152-24-048692-index.htm",
    "published_date": "2024-12-04",
    "source": "GlobalFoundries",
    "tags": null,
    "summary": null
  },
  {
    "axis": "foundry",
    "company": "globalfoundries",
    "category": "news",
    "headline": "8-K  - Current report",
    "url": "https://www.sec.gov/Archives/edgar/data/1826397/000149315224048183/0001493152-24-048183-index.htm",
    "published_date": "2024-11-29",
    "source": "GlobalFoundries",
    "tags": null,
    "summary": null
  },
  {
    "axis": "foundry",
    "company": "globalfoundries",
    "category": "news",
    "headline": "8-K  - Current report",
    "url": "https://www.sec.gov/Archives/edgar/data/1826397/000149315224044975/0001493152-24-044975-index.htm",
    "published_date": "2024-11-13",
    "source": "GlobalFoundries",
    "tags": null,
    "summary": null
  },
  {
    "axis": "foundry",
    "company": "globalfoundries",
    "category": "news",
    "headline": "8-K  - Current report",
    "url": "https://www.sec.gov/Archives/edgar/data/1826397/000149315224042788/0001493152-24-042788-index.htm",
    "published_date": "2024-10-29",
    "source": "GlobalFoundries",
    "tags": null,
    "summary": null
  },
  {
    "axis": "foundry",
    "company": "globalfoundries",
    "category": "news",
    "headline": "8-K  - Current report",
    "url": "https://www.sec.gov/Archives/edgar/data/1826397/000149315224041329/0001493152-24-041329-index.htm",
    "published_date": "2024-10-16",
    "source": "GlobalFoundries",
    "tags": null,
    "summary": null
  },
  {
    "axis": "foundry",
    "company": "globalfoundries",
    "category": "news",
    "headline": "8-K  - Current report",
    "url": "https://www.sec.gov/Archives/edgar/data/1826397/000149315224039395/0001493152-24-039395-index.htm",
    "published_date": "2024-10-03",
    "source": "GlobalFoundries",
    "tags": null,
    "summary": null
  },
  {
    "axis": "foundry",
    "company": "globalfoundries",
    "category": "news",
    "headline": "8-K  - Current report",
    "url": "https://www.sec.gov/Archives/edgar/data/1826397/000149315224038568/0001493152-24-038568-index.htm",
    "published_date": "2024-09-27",
    "source": "GlobalFoundries",
    "tags": null,
    "summary": null
  },
  {
    "axis": "foundry",
    "company": "globalfoundries",
    "category": "news",
    "headline": "8-K  - Current report",
    "url": "https://www.sec.gov/Archives/edgar/data/1826397/000149315224036407/0001493152-24-036407-index.htm",
    "published_date": "2024-09-16",
    "source": "GlobalFoundries",
    "tags": null,
    "summary": null
  },
  {
    "axis": "foundry",
    "company": "globalfoundries",
    "category": "news",
    "headline": "8-K  - Current report",
    "url": "https://www.sec.gov/Archives/edgar/data/1826397/000149315224033721/0001493152-24-033721-index.htm",
    "published_date": "2024-08-23",
    "source": "GlobalFoundries",
    "tags": null,
    "summary": null
  },
  {
    "axis": "foundry",
    "company": "globalfoundries",
    "category": "news",
    "headline": "8-K  - Current report",
    "url": "https://www.sec.gov/Archives/edgar/data/1826397/000149315224030256/0001493152-24-030256-index.htm",
    "published_date": "2024-08-05",
    "source": "GlobalFoundries",
    "tags": null,
    "summary": null
  },
  {
    "axis": "foundry",
    "company": "globalfoundries",
    "category": "news",
    "headline": "8-K  - Current report",
    "url": "https://www.sec.gov/Archives/edgar/data/1826397/000149315224026510/0001493152-24-026510-index.htm",
    "published_date": "2024-07-08",
    "source": "GlobalFoundries",
    "tags": null,
    "summary": null
  },
  {
    "axis": "foundry",
    "company": "globalfoundries",
    "category": "news",
    "headline": "8-K  - Current report",
    "url": "https://www.sec.gov/Archives/edgar/data/1826397/000149315224025623/0001493152-24-025623-index.htm",
    "published_date": "2024-06-28",
    "source": "GlobalFoundries",
    "tags": null,
    "summary": null
  },
  {
    "axis": "foundry",
    "company": "globalfoundries",
    "category": "news",
    "headline": "8-K  - Current report",
    "url": "https://www.sec.gov/Archives/edgar/data/1826397/000149315224023344/0001493152-24-023344-index.htm",
    "published_date": "2024-06-10",
    "source": "GlobalFoundries",
    "tags": null,
    "summary": null
  }
]